[
  {
    "orderId": "41d471b0",
    "name": "saravana Balaji",
    "phone": "7708479916",
    "address": "15,balaji street Cbe",
    "cart": {
      "1": 1
    },
    "image": null,
    "user_email": null,
    "created_at": 1765570432.8598802
  },
  {
    "orderId": "efded2e9",
    "name": "saravana Balaji",
    "phone": "7708479916",
    "address": "15,balaji street Cbe",
    "cart": {
      "4": 1
    },
    "image": null,
    "user_email": "parthipan.v.ciet@gmail.com",
    "created_at": 1765570629.580582
  },
  {
    "orderId": "184a64a7",
    "name": "saravana Balaji",
    "phone": "7708479916",
    "address": "summ",
    "cart": {
      "2": 1
    },
    "image": null,
    "user_email": null,
    "created_at": 1765571519.721462
  },
  {
    "orderId": "f9c1490b",
    "name": "saranya",
    "phone": "8807917718",
    "address": "summ",
    "cart": {
      "2": 1
    },
    "image": null,
    "user_email": null,
    "created_at": 1765571552.7466526
  },
  {
    "orderId": "6f7c05e3",
    "name": "Ruthra",
    "phone": "9361329489",
    "address": "summ",
    "cart": {
      "2": 2
    },
    "image": null,
    "user_email": null,
    "created_at": 1765571646.7230735
  }
]